scrap_engine/__init__.py
scrap_engine/consts.py
scrap_engine/error.py
scrap_engine/addable/__init__.py
scrap_engine/addable/addable.py
scrap_engine/addable/area.py
scrap_engine/addable/object.py
scrap_engine/addable/object_group.py
scrap_engine/addable/state.py
scrap_engine/addable/misc/__init__.py
scrap_engine/addable/misc/box.py
scrap_engine/addable/misc/circle.py
scrap_engine/addable/misc/frame.py
scrap_engine/addable/misc/line.py
scrap_engine/addable/misc/square.py
scrap_engine/addable/misc/text.py
scrap_engine/map/__init__.py
scrap_engine/map/map.py
scrap_engine/map/submap.py
scrap_engine-1.5.1.dist-info/licenses/LICENSE
scrap_engine-1.5.1.dist-info/METADATA
scrap_engine-1.5.1.dist-info/WHEEL
scrap_engine-1.5.1.dist-info/top_level.txt
scrap_engine-1.5.1.dist-info/RECORD
