Metadata-Version: 2.4
Name: scrap_engine
Version: 1.5.1
Summary: A 2D ascii game engine for the terminal
Author-email: lxgr <lxgr@protonmail.com>
License: GPL-3.0-only
Project-URL: Homepage, https://github.com/lxgr-linux/scrap_engine
Project-URL: Issues, https://github.com/lxgr-linux/scrap_engine/issue
Project-URL: Repository, https://github.com/lxgr-linux/scrap_engine.git
Keywords: game,Ascii
Classifier: Programming Language :: Python :: 3
Classifier: Operating System :: OS Independent
Requires-Python: >=3.12
License-File: LICENSE
Dynamic: license-file
